snovault/__init__.py
snovault/aggregated_items.py
snovault/app.py
snovault/appdefs.py
snovault/attachment.py
snovault/authentication.py
snovault/authorization.py
snovault/batchupgrade.py
snovault/cache.py
snovault/calculated.py
snovault/commands/__init__.py
snovault/commands/captured_output.py
snovault/commands/check_rendering.py
snovault/commands/clear_db_es_contents.py
snovault/commands/create_mapping_on_deploy.py
snovault/commands/es_index_data.py
snovault/commands/generate_local_access_key.py
snovault/commands/jsonld_rdf.py
snovault/commands/list_db_tables.py
snovault/commands/load_access_keys.py
snovault/commands/load_data.py
snovault/commands/load_data_by_type.py
snovault/commands/prepare_template.py
snovault/commands/profile.py
snovault/commands/purge_item_type.py
snovault/commands/run_upgrader_on_inserts.py
snovault/commands/update_inserts_from_server.py
snovault/commands/utils.py
snovault/commands/view_local_object.py
snovault/commands/wipe_test_indices.py
snovault/config.py
snovault/connection.py
snovault/crud_views.py
snovault/custom_embed.py
snovault/dev_servers.py
snovault/drs.py
snovault/edw_hash.py
snovault/elasticsearch/__init__.py
snovault/elasticsearch/cached_views.py
snovault/elasticsearch/create_mapping.py
snovault/elasticsearch/es_index_listener.py
snovault/elasticsearch/esstorage.py
snovault/elasticsearch/indexer.py
snovault/elasticsearch/indexer_queue.py
snovault/elasticsearch/indexer_utils.py
snovault/elasticsearch/interfaces.py
snovault/elasticsearch/mpindexer.py
snovault/embed.py
snovault/etag.py
snovault/indexing_views.py
snovault/ingestion/common.py
snovault/ingestion/exceptions.py
snovault/ingestion/ingestion_listener.py
snovault/ingestion/ingestion_listener_base.py
snovault/ingestion/ingestion_message.py
snovault/ingestion/ingestion_message_handler_decorator.py
snovault/ingestion/ingestion_message_handler_default.py
snovault/ingestion/ingestion_processor_decorator.py
snovault/ingestion/ingestion_processors.py
dcicsnovault-11.28.0.dist-info/LICENSE.txt
dcicsnovault-11.28.0.dist-info/METADATA
dcicsnovault-11.28.0.dist-info/WHEEL
dcicsnovault-11.28.0.dist-info/entry_points.txt
dcicsnovault-11.28.0.dist-info/RECORD
