Metadata-Version: 2.1
Name: dcicsnovault
Version: 11.28.0
Summary: Storage support for 4DN Data Portals.
Home-page: https://github.com/4dn-dcic/snovault
License: MIT
Author: 4DN-DCIC Team
Author-email: support@4dnucleome.org
Requires-Python: >=3.9,<3.13
Classifier: Development Status :: 4 - Beta
Classifier: Framework :: Pyramid
Classifier: Intended Audience :: Developers
Classifier: Intended Audience :: Science/Research
Classifier: License :: OSI Approved :: MIT License
Classifier: Programming Language :: Python :: 3
Classifier: Programming Language :: Python :: 3.9
Classifier: Programming Language :: Python :: 3.10
Classifier: Programming Language :: Python :: 3.11
Classifier: Programming Language :: Python :: 3
Classifier: Programming Language :: Python :: 3.10
Classifier: Programming Language :: Python :: 3.11
Classifier: Programming Language :: Python :: 3.12
Classifier: Programming Language :: Python :: 3.8
Classifier: Programming Language :: Python :: 3.9
Classifier: Topic :: Database :: Database Engines/Servers
Requires-Dist: PyBrowserID (>=0.10.0,<1)
Requires-Dist: SPARQLWrapper (>=1.8.5,<2.0.0)
Requires-Dist: SQLAlchemy (>=1.4.41,<2.0.0)
Requires-Dist: WSGIProxy2 (==0.4.2)
Requires-Dist: WebOb (>=1.8.7,<2.0.0)
Requires-Dist: WebTest (>=2.0.35,<3.0.0)
Requires-Dist: aws_requests_auth (>=0.4.3,<0.5.0)
Requires-Dist: boto3 (>=1.34.136,<2.0.0)
Requires-Dist: botocore (>=1.34.136,<2.0.0)
Requires-Dist: dcicutils (>=8.18.0,<9.0.0)
Requires-Dist: elasticsearch (==7.13.4)
Requires-Dist: elasticsearch_dsl (>=7.4.0,<8.0.0)
Requires-Dist: future (>=0.18.3,<0.19.0)
Requires-Dist: html5lib (>=1.1)
Requires-Dist: humanfriendly (>=1.44.9,<2.0.0)
Requires-Dist: jsonschema[format-nongpl] (>=4.19.0,<5.0.0)
Requires-Dist: netaddr (>=0.8.0,<1)
Requires-Dist: numpy (>=1.26.4,<2.0.0)
Requires-Dist: passlib (>=1.7.4,<2.0.0)
Requires-Dist: pillow (>=11.1.0,<12.0.0)
Requires-Dist: pmdarima (>=2.0.4,<3.0.0)
Requires-Dist: psutil (>=5.9.0,<6.0.0)
Requires-Dist: psycopg2-binary (>=2.9.1,<3.0.0)
Requires-Dist: pyjwt (>=2.6.0,<3.0.0)
Requires-Dist: pyramid (==1.10.8)
Requires-Dist: pyramid-multiauth (>=0.9.0,<1)
Requires-Dist: pyramid-retry (>=1.0,<2.0)
Requires-Dist: pyramid-tm (>=2.5,<3.0)
Requires-Dist: pyramid-translogger (>=0.1,<0.2)
Requires-Dist: python-dateutil (>=2.8.2,<3.0.0)
Requires-Dist: python_magic (>=0.4.27)
Requires-Dist: pytz (>=2021.3)
Requires-Dist: rdflib (>=4.2.2,<5.0.0)
Requires-Dist: rdflib-jsonld (>=0.5.0,<1.0.0)
Requires-Dist: redis (>=4.5.1,<5.0.0)
Requires-Dist: rutter (>=0.3,<1)
Requires-Dist: simplejson (>=3.17.6,<4.0.0)
Requires-Dist: structlog (>=19.2.0,<20)
Requires-Dist: subprocess_middleware (>=0.3,<1)
Requires-Dist: transaction (>=3.0.1,<4.0.0)
Requires-Dist: venusian (>=3.1.0,<4.0.0)
Requires-Dist: xlrd (>=1.0.0,<2.0.0)
Requires-Dist: zope.deprecation (>=4.4.0,<5.0.0)
Requires-Dist: zope.interface (>=4.7.2,<6)
Requires-Dist: zope.sqlalchemy (==1.6)
Project-URL: Documentation, https://github.com/4dn-dcic/snovault
Project-URL: Repository, https://github.com/4dn-dcic/snovault
